[
  {
    "scientific_name": "Pantherophis Guttatus",
    "category": "Serpent",
    "family": "Colubridés",
    "venomous": false,
    "fr": {
      "name": "Couleuvre à blé",
      "diet": "Rongeur",
      "repro": "Ovipare"
    },
    "en": {
      "name": "Corn Snake",
      "diet": "Rodent",
      "repro": "Oviparous"
    },
    "es": {
      "name": "Culebra de maiz",
      "diet": "Roedor",
      "repro": "Ovíparo"
    },
    "de": {
      "name": "Kornnatter",
      "diet": "Nagetier",
      "repro": "Ovipar"
    },
    "zh": {
      "name": "玉米蛇",
      "diet": "啮齿动物",
      "repro": "卵生"
    },
    "nl": {
      "name": "Korenslang",
      "diet": "Knaagdier",
      "repro": "Eierleggend"
    }
  },
  {
    "scientific_name": "Heterodon Nasicus",
    "category": "Serpent",
    "family": "Colubridés",
    "venomous": true,
    "fr": {
      "name": "Hétérodon",
      "diet": "Rongeur/Amphibien",
      "repro": "Ovipare"
    },
    "en": {
      "name": "Western Hognose",
      "diet": "Rodent/Amphibian",
      "repro": "Oviparous"
    },
    "es": {
      "name": "Falsa coral",
      "diet": "Roedor/Anfibio",
      "repro": "Ovíparo"
    },
    "de": {
      "name": "Halsbandnatter",
      "diet": "Nagetier/Amphibie",
      "repro": "Ovipar"
    },
    "zh": {
      "name": "猪鼻蛇",
      "diet": "啮齿动物/两栖动物",
      "repro": "卵生"
    },
    "nl": {
      "name": "Westelijke haakneusslang",
      "diet": "Knaagdier/Amfibie",
      "repro": "Eierleggend"
    }
  },
  {
    "scientific_name": "Dasypeltis Scabra",
    "category": "Serpent",
    "family": "Colubridés",
    "venomous": false,
    "fr": {
      "name": "Couleuvre mangeuse d'oeufs",
      "diet": "Oeuf",
      "repro": "Ovipare"
    },
    "en": {
      "name": "Egg-eating Snake",
      "diet": "Egg",
      "repro": "Oviparous"
    },
    "es": {
      "name": "Culebra comedora de huevos",
      "diet": "Huevo",
      "repro": "Ovíparo"
    },
    "de": {
      "name": "Afrikanische Eierschlange",
      "diet": "Ei",
      "repro": "Ovipar"
    },
    "zh": {
      "name": "食卵蛇",
      "diet": "蛋",
      "repro": "卵生"
    },
    "nl": {
      "name": "Eieretende slang",
      "diet": "Ei",
      "repro": "Eierleggend"
    }
  },
  {
    "scientific_name": "Python Regius",
    "category": "Serpent",
    "family": "Pythons",
    "venomous": false,
    "fr": {
      "name": "Python Royal",
      "diet": "Rongeur",
      "repro": "Ovipare"
    },
    "en": {
      "name": "Ball Python",
      "diet": "Rodent",
      "repro": "Oviparous"
    },
    "es": {
      "name": "Pitón Real",
      "diet": "Roedor",
      "repro": "Ovíparo"
    },
    "de": {
      "name": "Königspython",
      "diet": "Nagetier",
      "repro": "Ovipar"
    },
    "zh": {
      "name": "球蟒",
      "diet": "啮齿动物",
      "repro": "卵生"
    },
    "nl": {
      "name": "Koningspython",
      "diet": "Knaagdier",
      "repro": "Eierleggend"
    }
  },
  {
    "scientific_name": "Morelia Viridis",
    "category": "Serpent",
    "family": "Pythons",
    "venomous": false,
    "fr": {
      "name": "Python Vert",
      "diet": "Rongeur/Oiseau",
      "repro": "Ovipare"
    },
    "en": {
      "name": "Green Tree Python",
      "diet": "Rodent/Bird",
      "repro": "Oviparous"
    },
    "es": {
      "name": "Pitón de árbol verde",
      "diet": "Roedor/Ave",
      "repro": "Ovíparo"
    },
    "de": {
      "name": "Grüner Baumpython",
      "diet": "Nagetier/Vogel",
      "repro": "Ovipar"
    },
    "zh": {
      "name": "绿树蟒",
      "diet": "啮齿动物/鸟类",
      "repro": "卵生"
    },
    "nl": {
      "name": "Groene boompython",
      "diet": "Knaagdier/Vogel",
      "repro": "Eierleggend"
    }
  },
  {
    "scientific_name": "Boa Imperator",
    "category": "Serpent",
    "family": "Boas",
    "venomous": false,
    "fr": {
      "name": "Boa Imperator",
      "diet": "Rongeur",
      "repro": "Ovovivipare"
    },
    "en": {
      "name": "Boa Imperator",
      "diet": "Rodent",
      "repro": "Ovoviviparous"
    },
    "es": {
      "name": "Boa Imperator",
      "diet": "Roedor",
      "repro": "Ovovivíparo"
    },
    "de": {
      "name": "Kaiserboa",
      "diet": "Nagetier",
      "repro": "Ovovivipar"
    },
    "zh": {
      "name": "巨蚺",
      "diet": "啮齿动物",
      "repro": "卵胎生"
    },
    "nl": {
      "name": "Keizerboa",
      "diet": "Knaagdier",
      "repro": "Eierlevendbarend"
    }
  },
  {
    "scientific_name": "Eryx Colubrinus",
    "category": "Serpent",
    "family": "Boas",
    "venomous": false,
    "fr": {
      "name": "Boa de sable",
      "diet": "Rongeur",
      "repro": "Ovovivipare"
    },
    "en": {
      "name": "Kenyan Sand Boa",
      "diet": "Rodent",
      "repro": "Ovoviviparous"
    },
    "es": {
      "name": "Boa de arena",
      "diet": "Roedor",
      "repro": "Ovovivíparo"
    },
    "de": {
      "name": "Kenya-Sandboa",
      "diet": "Nagetier",
      "repro": "Ovovivipar"
    },
    "zh": {
      "name": "肯尼亚沙蚺",
      "diet": "啮齿动物",
      "repro": "卵胎生"
    },
    "nl": {
      "name": "Keniaanse zandboa",
      "diet": "Knaagdier",
      "repro": "Eierlevendbarend"
    }
  },
  {
    "scientific_name": "Crotalus Atrox",
    "category": "Serpent",
    "family": "Venimeux",
    "venomous": true,
    "fr": {
      "name": "Crotale diamantin",
      "diet": "Rongeur/Lapin",
      "repro": "Ovovivipare"
    },
    "en": {
      "name": "Western Diamondback",
      "diet": "Rodent/Rabbit",
      "repro": "Ovoviviparous"
    },
    "es": {
      "name": "Cascabel diamantina",
      "diet": "Roedor/Conejo",
      "repro": "Ovovivíparo"
    },
    "de": {
      "name": "Texanische Klapperschlange",
      "diet": "Nagetier/Kaninchen",
      "repro": "Ovovivipar"
    },
    "zh": {
      "name": "西部菱背响尾蛇",
      "diet": "啮齿动物/兔子",
      "repro": "卵胎生"
    },
    "nl": {
      "name": "Westerse diamantratelslang",
      "diet": "Knaagdier/Konijn",
      "repro": "Eierlevendbarend"
    }
  },
  {
    "scientific_name": "Pogona Vitticeps",
    "category": "Lézard",
    "family": "Agames",
    "venomous": false,
    "fr": {
      "name": "Pogona",
      "diet": "Insectivore",
      "repro": "Ovipare"
    },
    "en": {
      "name": "Bearded Dragon",
      "diet": "Insectivore",
      "repro": "Oviparous"
    },
    "es": {
      "name": "Dragón Barbudo",
      "diet": "Insectívoro",
      "repro": "Ovíparo"
    },
    "de": {
      "name": "Bartagame",
      "diet": "Insektenfresser",
      "repro": "Ovipar"
    },
    "zh": {
      "name": "鬃狮蜥",
      "diet": "食虫动物",
      "repro": "卵生"
    },
    "nl": {
      "name": "Baardagame",
      "diet": "Insecteneter",
      "repro": "Eierleggend"
    }
  },
  {
    "scientific_name": "Eublepharis Macularius",
    "category": "Lézard",
    "family": "Geckos",
    "venomous": false,
    "fr": {
      "name": "Gecko Léopard",
      "diet": "Insectivore",
      "repro": "Ovipare"
    },
    "en": {
      "name": "Leopard Gecko",
      "diet": "Insectivore",
      "repro": "Oviparous"
    },
    "es": {
      "name": "Gecko Leopardo",
      "diet": "Insectívoro",
      "repro": "Ovíparo"
    },
    "de": {
      "name": "Leopardgecko",
      "diet": "Insektenfresser",
      "repro": "Ovipar"
    },
    "zh": {
      "name": "豹纹守宫",
      "diet": "食虫动物",
      "repro": "卵生"
    },
    "nl": {
      "name": "Luipaardgekko",
      "diet": "Insecteneter",
      "repro": "Eierleggend"
    }
  },
  {
    "scientific_name": "Correlophus Ciliatus",
    "category": "Lézard",
    "family": "Geckos",
    "venomous": false,
    "fr": {
      "name": "Gecko à Crête",
      "diet": "Insectivore",
      "repro": "Ovipare"
    },
    "en": {
      "name": "Crested Gecko",
      "diet": "Insectivore",
      "repro": "Oviparous"
    },
    "es": {
      "name": "Gecko Crestado",
      "diet": "Insectívoro",
      "repro": "Ovíparo"
    },
    "de": {
      "name": "Kronengecko",
      "diet": "Insektenfresser",
      "repro": "Ovipar"
    },
    "zh": {
      "name": "睫角守宫",
      "diet": "食虫动物",
      "repro": "卵生"
    },
    "nl": {
      "name": "Wimpergekko",
      "diet": "Insecteneter",
      "repro": "Eierleggend"
    }
  },
  {
    "scientific_name": "Testudo Hermanni",
    "category": "Tortue",
    "family": "Terrestre",
    "venomous": false,
    "fr": {
      "name": "Tortue d'Hermann",
      "diet": "Herbivore",
      "repro": "Ovipare"
    },
    "en": {
      "name": "Hermann's Tortoise",
      "diet": "Herbivore",
      "repro": "Oviparous"
    },
    "es": {
      "name": "Tortuga de Hermann",
      "diet": "Herbívoro",
      "repro": "Ovíparo"
    },
    "de": {
      "name": "Griechische Landschildkröte",
      "diet": "Pflanzenfresser",
      "repro": "Ovipar"
    },
    "zh": {
      "name": "赫曼陆龟",
      "diet": "食草动物",
      "repro": "卵生"
    },
    "nl": {
      "name": "Griekse landschildpad",
      "diet": "Planteneter",
      "repro": "Eierleggend"
    }
  },
  {
    "scientific_name": "Ambystoma Mexicanum",
    "category": "Amphibien",
    "family": "Urodèles",
    "venomous": false,
    "fr": {
      "name": "Axolotl",
      "diet": "Carnivore",
      "repro": "Ovipare"
    },
    "en": {
      "name": "Axolotl",
      "diet": "Carnivore",
      "repro": "Oviparous"
    },
    "es": {
      "name": "Ajolote",
      "diet": "Carnívoro",
      "repro": "Ovíparo"
    },
    "de": {
      "name": "Axolotl",
      "diet": "Fleischfresser",
      "repro": "Ovipar"
    },
    "zh": {
      "name": "美西螈",
      "diet": "食肉动物",
      "repro": "卵生"
    },
    "nl": {
      "name": "Axolotl",
      "diet": "Vleeseter",
      "repro": "Eierleggend"
    }
  }
]